{
    "wallpaper": "/home/andrew/.config/wpg/wallpapers/fluidSim.jpg",
    "alpha": "100",

    "special": {
        "background": "#000008",
        "foreground": "#ffffff",
        "cursor": "#ffffff"
    },
    "colors": {
        "color0": "#000008",
        "color1": "#2296d7",
        "color2": "#60d338",
        "color3": "#c92c78",
        "color4": "#eae248",
        "color5": "#dd1243",
        "color6": "#6b6ce3",
        "color7": "#ffffff",
        "color8": "#454567",
        "color9": "#2296d7",
        "color10": "#60d338",
        "color11": "#c92c78",
        "color12": "#eae248",
        "color13": "#dd1243",
        "color14": "#6b6ce3",
        "color15": "#ffffff"
    }
}
